README.md
configs/callbacks/default.yaml
configs/callbacks/early_stopping.yaml
configs/callbacks/layer_freeze.yaml
configs/callbacks/learning_rate_monitor.yaml
configs/callbacks/model_checkpoint.yaml
configs/callbacks/model_summary.yaml
configs/callbacks/none.yaml
configs/callbacks/outlier_detection.yaml
configs/callbacks/rich_progress_bar.yaml
configs/compile.yaml
configs/data/classification/single_timepoint.yaml
configs/data/contrastive/vicreg.yaml
configs/data/im2im/diffae.yaml
configs/data/im2im/gan.yaml
configs/data/im2im/gan_superres.yaml
configs/data/im2im/ijepa.yaml
configs/data/im2im/instance_seg.yaml
configs/data/im2im/iwm.yaml
configs/data/im2im/labelfree.yaml
configs/data/im2im/mae.yaml
configs/data/im2im/multidim.yaml
configs/data/im2im/numpy_dataloader_predict.yaml
configs/data/im2im/numpy_dataloader_train.yaml
configs/data/im2im/segmentation.yaml
configs/data/im2im/segmentation_plugin.yaml
configs/data/im2im/segmentation_superres.yaml
configs/data/private/lattice_nuc_sdf.yaml
configs/data/private/rot_mnist.yaml
configs/data/private/rot_mnist_vae.yaml
configs/data/private/rotated_mnist.yaml
configs/data/private/variance_3d.yaml
configs/data/private/variance_3d_npm1.yaml
configs/data/private/variance_3d_npm_nuc_v2.yaml
configs/data/private/variance_3d_rotate.yaml
configs/data/private/variance_centerslice.yaml
configs/data/private/variance_centerslice_resize.yaml
configs/data/private/variance_npm1.yaml
configs/data/private/variance_spharm.yaml
configs/data/test/alternating_batch.yaml
configs/data/test/omnipose.yaml
configs/data/test/segmentation.yaml
configs/debug/default.yaml
configs/debug/fdr.yaml
configs/debug/limit.yaml
configs/debug/overfit.yaml
configs/debug/profiler.yaml
configs/eval.yaml
configs/experiment/classification/per_timepoint.yaml
configs/experiment/contrastive/vicreg.yaml
configs/experiment/im2im/diffae.yaml
configs/experiment/im2im/gan.yaml
configs/experiment/im2im/gan_superres.yaml
configs/experiment/im2im/hiera.yaml
cyto_dl-0.6.1.dist-info/WHEEL
cyto_dl-0.6.1.dist-info/METADATA
cyto_dl-0.6.1.dist-info/RECORD
