Metadata-Version: 2.1
Name: cyto-dl
Version: 0.6.1
Summary: Collection of representation learning models, techniques, callbacks, utils, used to create latent variable models of cell shape, morphology and intracellular organization.
Author-email: Benji Morris <benjamin.morris@alleninstitute.org>,Guilherme Pires <guilherme.pires@alleninstitute.org>,Ritvik Vasan <ritvik.vasan@alleninstitute.org>
Requires-Python: >=3.9,<3.12
Requires-Dist: PyYAML>=6.0
Requires-Dist: anndata>=0.8
Requires-Dist: astropy>=5.2
Requires-Dist: bioio-base!=1.0.5,!=1.0.6
Requires-Dist: bioio-czi
Requires-Dist: bioio-ome-tiff
Requires-Dist: bioio-tifffile
Requires-Dist: bioio>=1.0.1
Requires-Dist: boto3
Requires-Dist: edt>=3.0.0
Requires-Dist: einops>=0.6.1
Requires-Dist: fire>=0.5
Requires-Dist: hydra-colorlog>=1.2
Requires-Dist: hydra-core~=1.3.0
Requires-Dist: hydra-optuna-sweeper>=1.2
Requires-Dist: lightning>=2.0
Requires-Dist: matplotlib>=3.7
Requires-Dist: mlflow>=2.1
Requires-Dist: monai>=1.4
Requires-Dist: numpy>=1.23
Requires-Dist: ome-zarr>=0.6
Requires-Dist: omegaconf>=2.3
Requires-Dist: online-stats>=2023
Requires-Dist: opencv-python>=4.10.0
Requires-Dist: pandas>=1.5
Requires-Dist: positional-encodings>=6.0.3
Requires-Dist: pyarrow>=10.0
Requires-Dist: pyrootutils>=1.0
Requires-Dist: rich
Requires-Dist: scikit-learn>=1.2
Requires-Dist: tifffile<2025.2.18,>=2024.0.0
Requires-Dist: timm>=0.9.7
Requires-Dist: torch~=2.0.0
Requires-Dist: tqdm>=4.64
Requires-Dist: universal-pathlib>=0.0
Provides-Extra: all
Requires-Dist: cyto-dl[equiv,pcloud,s3,spharm,torchserve]; extra == "all"
Provides-Extra: docs
Requires-Dist: cyto-dl; extra == "docs"
Requires-Dist: furo<=2023.3.23; extra == "docs"
Requires-Dist: m2r2<=0.3.3.post2; extra == "docs"
Requires-Dist: sphinx<=6.1.3; extra == "docs"
Provides-Extra: equiv
Requires-Dist: lie_learn==0.0.1.post1; extra == "equiv"
Requires-Dist: escnn~=1.0.7; extra == "equiv"
Requires-Dist: py3nj>=0.2.1; extra == "equiv"
Requires-Dist: e3nn~=0.5.1; extra == "equiv"
Provides-Extra: pcloud
Requires-Dist: pyntcloud>=0.3.1; extra == "pcloud"
Requires-Dist: aicsshparam>=0.1.7; extra == "pcloud"
Requires-Dist: torch-geometric>=2.3.1; extra == "pcloud"
Requires-Dist: point-cloud-utils>=0.29.6; extra == "pcloud"
Requires-Dist: geomloss>=0.2.6; extra == "pcloud"
Requires-Dist: Ninja>=1.11.1; extra == "pcloud"
Requires-Dist: torchio>=0.19.1; extra == "pcloud"
Provides-Extra: s3
Requires-Dist: boto3<1.24.5,>=1.23.5; extra == "s3"
Requires-Dist: s3fs~=2023.1; extra == "s3"
Provides-Extra: spharm
Requires-Dist: vtk~=9.2; extra == "spharm"
Requires-Dist: aicscytoparam~=0.1; extra == "spharm"
Requires-Dist: pyshtools==4.10.3; extra == "spharm"
Provides-Extra: test
Requires-Dist: cyto-dl; extra == "test"
Requires-Dist: pytest~=7.2; extra == "test"
Requires-Dist: pytest-cov[toml]~=4.0; extra == "test"
Provides-Extra: torchserve
Requires-Dist: torchserve>=0.8.0; extra == "torchserve"
Requires-Dist: gorilla>=0.4.0; extra == "torchserve"
Project-URL: Homepage, https://github.com/AllenCellModeling/cyto-dl
